cijoe/fio/__init__.py
cijoe/fio/wrapper.py
cijoe/fio/configs/__init__.py
cijoe/fio/configs/default-config.toml
cijoe/fio/scripts/__init__.py
cijoe/fio/scripts/build.py
cijoe/fio/scripts/check.py
cijoe/fio/scripts/install.py
cijoe/fio/selftest/__init__.py
cijoe/fio/selftest/test_fio_wrapper.py
cijoe/fio/workflows/__init__.py
cijoe/fio/workflows/example.workflow
cijoe_pkg_fio-0.9.7.dist-info/LICENSE
cijoe_pkg_fio-0.9.7.dist-info/METADATA
cijoe_pkg_fio-0.9.7.dist-info/WHEEL
cijoe_pkg_fio-0.9.7.dist-info/top_level.txt
cijoe_pkg_fio-0.9.7.dist-info/RECORD
